formulae/__init__.py
formulae/categorical.py
formulae/config.py
formulae/contrasts.py
formulae/environment.py
formulae/expr.py
formulae/matrices.py
formulae/model_description.py
formulae/parser.py
formulae/resolver.py
formulae/scanner.py
formulae/token.py
formulae/transforms.py
formulae/utils.py
formulae/examples/Examples.ipynb
formulae/examples/Features.ipynb
formulae/terms/__init__.py
formulae/terms/call.py
formulae/terms/call_resolver.py
formulae/terms/call_utils.py
formulae/terms/terms.py
formulae/terms/variable.py
formulae-0.6.0.dist-info/licenses/LICENSE
formulae-0.6.0.dist-info/METADATA
formulae-0.6.0.dist-info/WHEEL
formulae-0.6.0.dist-info/top_level.txt
formulae-0.6.0.dist-info/RECORD
