Metadata-Version: 2.4
Name: formulae
Version: 0.6.0
Summary: Formulas for mixed-effects models in Python
Maintainer-email: Tomás Capretto <tomicapretto@gmail.com>
License: MIT License
Project-URL: homepage, https://bambinos.github.io/formulae
Project-URL: documentation, https://bambinos.github.io/formulae
Project-URL: repository, https://github.com/bambinos/formulae
Project-URL: changelog, https://github.com/bambinos/formulae/blob/main/docs/CHANGELOG.md
Requires-Python: >=3.8
License-File: LICENSE
Requires-Dist: numpy>=1.16
Requires-Dist: packaging
Requires-Dist: pandas>=1.0.0
Requires-Dist: scipy>=1.5.4
Dynamic: license-file
